trytond/modules/country/__init__.py
trytond/modules/country/country.py
trytond/modules/country/country.xml
trytond/modules/country/organization.xml
trytond/modules/country/region.xml
trytond/modules/country/tryton.cfg
trytond/modules/country/icons/tryton-country.svg
trytond/modules/country/locale/bg.po
trytond/modules/country/locale/ca.po
trytond/modules/country/locale/cs.po
trytond/modules/country/locale/de.po
trytond/modules/country/locale/es.po
trytond/modules/country/locale/es_419.po
trytond/modules/country/locale/et.po
trytond/modules/country/locale/fa.po
trytond/modules/country/locale/fi.po
trytond/modules/country/locale/fr.po
trytond/modules/country/locale/hu.po
trytond/modules/country/locale/id.po
trytond/modules/country/locale/it.po
trytond/modules/country/locale/lo.po
trytond/modules/country/locale/lt.po
trytond/modules/country/locale/nl.po
trytond/modules/country/locale/pl.po
trytond/modules/country/locale/pt.po
trytond/modules/country/locale/ro.po
trytond/modules/country/locale/ru.po
trytond/modules/country/locale/sl.po
trytond/modules/country/locale/tr.po
trytond/modules/country/locale/uk.po
trytond/modules/country/locale/zh_CN.po
trytond/modules/country/scripts/__init__.py
trytond/modules/country/scripts/import_countries.py
trytond/modules/country/scripts/import_postal_codes.py
trytond/modules/country/tests/__init__.py
trytond/modules/country/tests/scenario_country_import.rst
trytond/modules/country/tests/test_module.py
trytond/modules/country/tests/test_scenario.py
trytond/modules/country/view/country_form.xml
trytond/modules/country/view/country_tree.xml
trytond/modules/country/view/organization_form.xml
trytond/modules/country/view/organization_list.xml
trytond/modules/country/view/organization_member_form.xml
trytond/modules/country/view/organization_member_list.xml
trytond/modules/country/view/postal_code_form.xml
trytond/modules/country/view/postal_code_list.xml
trytond/modules/country/view/region_form.xml
trytond_country-7.6.0.dist-info/licenses/LICENSE
trytond_country-7.6.0.dist-info/METADATA
trytond_country-7.6.0.dist-info/WHEEL
trytond_country-7.6.0.dist-info/entry_points.txt
trytond_country-7.6.0.dist-info/top_level.txt
trytond_country-7.6.0.dist-info/RECORD
